Workbook

Sheet Assumptions
A1: SUBSCRIPTION TRACKER — FREEMIUM MODEL ASSUMPTIONS
A3: PRICING & FEES
A4: Parameter | B4: Value | C4: Format | D4: Notes
A5: Pro Unlock Price | B5: 4.99 | D5: One-time lifetime unlock
A6: Apple/Google Commission | B6: 0.15 | D6: 15% Small Business Program (under $1M rev)
A7: Net Revenue per Sale | B7: =B5*(1-B6) -> 4.2415 | D7: After platform cut
A9: AI COSTS (Claude Haiku 4.5)
A10: Parameter | B10: Value | C10: Format | D10: Notes
A11: Cost per AI Scan | B11: 0.00151 | D11: Image + prompt + output
A12: Free Tier AI Scans (taster) | B12: 3 | D12: Three free scans per free user (handles 1 bad + 2 good)
A13: Pro User Scans/Month | B13: 3 | D13: Average monthly scans for paying users
A14: Free User Monthly Cost | B14: =B11*B12 -> 0.00453 | D14: One-time taster cost only
A15: Pro User Monthly AI Cost | B15: =B11*B13 -> 0.00453 | D15: Per paying user per month
A17: GROWTH & CONVERSION
A18: Parameter | B18: Value | C18: Format | D18: Notes
A19: Year 1 Total Downloads | B19: 50000 | D19: Free + paid combined
A20: Year 2 Total Downloads | B20: 100000 | D20: Growing awareness
A21: Year 3 Total Downloads | B21: 200000 | D21: Established presence
A22: Year 4 Total Downloads | B22: 300000 | D22: Mature growth
A23: Year 5 Total Downloads | B23: 350000 | D23: Plateau
A24: Conversion Rate (Free → Pro) | B24: 0.04 | D24: Industry avg 2-5%, we target 4%
A25: Free User Annual Retention | B25: 0.3 | D25: Free users churn faster
A26: Pro User Annual Retention | B26: 0.7 | D26: Paid users stick around
A28: FIXED COSTS
A29: Parameter | B29: Value | C29: Format | D29: Notes
A30: Monthly Hosting (Firebase) | B30: 25 | D30: Scales with users
A31: Apple Dev Account (Annual) | B31: 99 | D31: $8.25/month
A32: Google Play Fee (One-time) | B32: 25 | D32: One-time $25

Sheet 5-Year Projection
A1: FREEMIUM MODEL — 5-YEAR PROJECTION (ACCUMULATING USERS)
A3: Metric | B3: Year 1 | C3: Year 2 | D3: Year 3 | E3: Year 4 | F3: Year 5
A4: DOWNLOADS & USERS
A5: New Downloads (total) | B5: =Assumptions!B19 -> 50000 | C5: =Assumptions!B20 -> 100000 | D5: =Assumptions!B21 -> 200000 | E5: =Assumptions!B22 -> 300000 | F5: =Assumptions!B23 -> 350000
A6: New Free Users (non-converting) | B6: =B5*(1-Assumptions!$B$24) -> 48000 | C6: =C5*(1-Assumptions!$B$24) -> 96000 | D6: =D5*(1-Assumptions!$B$24) -> 192000 | E6: =E5*(1-Assumptions!$B$24) -> 288000 | F6: =F5*(1-Assumptions!$B$24) -> 336000
A7: New Pro Conversions | B7: =B5*Assumptions!$B$24 -> 2000 | C7: =C5*Assumptions!$B$24 -> 4000 | D7: =D5*Assumptions!$B$24 -> 8000 | E7: =E5*Assumptions!$B$24 -> 12000 | F7: =F5*Assumptions!$B$24 -> 14000
A8: Retained Free Users (from prior years) | B8: 0 | C8: =B10*Assumptions!$B$25 -> 14400 | D8: =C10*Assumptions!$B$25 -> 33120 | E8: =D10*Assumptions!$B$25 -> 67536 | F8: =E10*Assumptions!$B$25 -> 106660.8
A9: Retained Pro Users (from prior years) | B9: 0 | C9: =B11*Assumptions!$B$26 -> 1400 | D9: =C11*Assumptions!$B$26 -> 3780 | E9: =D11*Assumptions!$B$26 -> 8246 | F9: =E11*Assumptions!$B$26 -> 14172.2
A10: Total Active Free Users | B10: =B6+B8 -> 48000 | C10: =C6+C8 -> 110400 | D10: =D6+D8 -> 225120 | E10: =E6+E8 -> 355536 | F10: =F6+F8 -> 442660.8
A11: Total Active Pro Users | B11: =B7+B9 -> 2000 | C11: =C7+C9 -> 5400 | D11: =D7+D9 -> 11780 | E11: =E7+E9 -> 20246 | F11: =F7+F9 -> 28172.2
A12: Total Active Users | B12: =B10+B11 -> 50000 | C12: =C10+C11 -> 115800 | D12: =D10+D11 -> 236900 | E12: =E10+E11 -> 375782 | F12: =F10+F11 -> 470833
A14: REVENUE
A15: Gross Revenue (new Pro sales) | B15: =B7*Assumptions!$B$5 -> 9980 | C15: =C7*Assumptions!$B$5 -> 19960 | D15: =D7*Assumptions!$B$5 -> 39920 | E15: =E7*Assumptions!$B$5 -> 59880 | F15: =F7*Assumptions!$B$5 -> 69860
A16: Platform Commission (15%) | B16: =B15*Assumptions!$B$6 -> 1497 | C16: =C15*Assumptions!$B$6 -> 2994 | D16: =D15*Assumptions!$B$6 -> 5988 | E16: =E15*Assumptions!$B$6 -> 8982 | F16: =F15*Assumptions!$B$6 -> 10479
A17: Net Revenue | B17: =B15-B16 -> 8483 | C17: =C15-C16 -> 16966 | D17: =D15-D16 -> 33932 | E17: =E15-E16 -> 50898 | F17: =F15-F16 -> 59381
A19: AI COSTS
A20: Taster Scans (new free users × 1) | B20: =B6*Assumptions!$B$12*Assumptions!$B$11 -> 217.44 | C20: =C6*Assumptions!$B$12*Assumptions!$B$11 -> 434.88 | D20: =D6*Assumptions!$B$12*Assumptions!$B$11 -> 869.76 | E20: =E6*Assumptions!$B$12*Assumptions!$B$11 -> 1304.64 | F20: =F6*Assumptions!$B$12*Assumptions!$B$11 -> 1522.08
A21: Pro User Scans (total pro × 3/mo × 12) | B21: =B11*Assumptions!$B$13*12*Assumptions!$B$11 -> 108.72 | C21: =C11*Assumptions!$B$13*12*Assumptions!$B$11 -> 293.544 | D21: =D11*Assumptions!$B$13*12*Assumptions!$B$11 -> 640.3608 | E21: =E11*Assumptions!$B$13*12*Assumptions!$B$11 -> 1100.5726 | F21: =F11*Assumptions!$B$13*12*Assumptions!$B$11 -> 1531.4408
A22: Total Annual AI Scans | B22: =(B6*Assumptions!$B$12)+(B11*Assumptions!$B$13*12) -> 216000 | C22: =(C6*Assumptions!$B$12)+(C11*Assumptions!$B$13*12) -> 482400 | D22: =(D6*Assumptions!$B$12)+(D11*Assumptions!$B$13*12) -> 1000080 | E22: =(E6*Assumptions!$B$12)+(E11*Assumptions!$B$13*12) -> 1592856 | F22: =(F6*Assumptions!$B$12)+(F11*Assumptions!$B$13*12) -> 2022199.2
A23: Total AI Cost | B23: =B20+B21 -> 326.16 | C23: =C20+C21 -> 728.424 | D23: =D20+D21 -> 1510.1208 | E23: =E20+E21 -> 2405.2126 | F23: =F20+F21 -> 3053.5208
A25: FIXED COSTS
A26: Hosting (scales with users) | B26: =(Assumptions!$B$30+(B12/10000)*5)*12 -> 600 | C26: =(Assumptions!$B$30+(C12/10000)*5)*12 -> 994.8 | D26: =(Assumptions!$B$30+(D12/10000)*5)*12 -> 1721.4 | E26: =(Assumptions!$B$30+(E12/10000)*5)*12 -> 2554.692 | F26: =(Assumptions!$B$30+(F12/10000)*5)*12 -> 3124.998
A27: Apple Dev Account | B27: =Assumptions!$B$31 -> 99 | C27: =Assumptions!$B$31 -> 99 | D27: =Assumptions!$B$31 -> 99 | E27: =Assumptions!$B$31 -> 99 | F27: =Assumptions!$B$31 -> 99
A28: Google Play Fee | B28: =Assumptions!$B$32 -> 25 | C28: 0 | D28: 0 | E28: 0 | F28: 0
A29: Total Fixed Costs | B29: =B26+B27+B28 -> 724 | C29: =C26+C27+C28 -> 1093.8 | D29: =D26+D27+D28 -> 1820.4 | E29: =E26+E27+E28 -> 2653.692 | F29: =F26+F27+F28 -> 3223.998
A31: PROFITABILITY
A32: Total Costs | B32: =B23+B29 -> 1050.16 | C32: =C23+C29 -> 1822.224 | D32: =D23+D29 -> 3330.5208 | E32: =E23+E29 -> 5058.9046 | F32: =F23+F29 -> 6277.5188
A33: Net Profit | B33: =B17-B32 -> 7432.84 | C33: =C17-C32 -> 15143.776 | D33: =D17-D32 -> 30601.479 | E33: =E17-E32 -> 45839.095 | F33: =F17-F32 -> 53103.481
A34: Profit Margin | B34: =IF(B17>0,B33/B17,0) -> 0.87620417 | C34: =IF(C17>0,C33/C17,0) -> 0.89259554 | D34: =IF(D17>0,D33/D17,0) -> 0.9018472 | E34: =IF(E17>0,E33/E17,0) -> 0.90060701 | F34: =IF(F17>0,F33/F17,0) -> 0.89428405
A35: Cumulative Profit | B35: =B33 -> 7432.84 | C35: =B35+C33 -> 22576.616 | D35: =C35+D33 -> 53178.095 | E35: =D35+E33 -> 99017.191 | F35: =E35+F33 -> 152120.67
A37: UNIT ECONOMICS
A38: Revenue per Pro User | B38: =IF(B7>0,B17/B7,0) -> 4.2415 | C38: =IF(C7>0,C17/C7,0) -> 4.2415 | D38: =IF(D7>0,D17/D7,0) -> 4.2415 | E38: =IF(E7>0,E17/E7,0) -> 4.2415 | F38: =IF(F7>0,F17/F7,0) -> 4.2415
A39: AI Cost per Pro User (annual) | B39: =Assumptions!$B$13*12*Assumptions!$B$11 -> 0.05436 | C39: =Assumptions!$B$13*12*Assumptions!$B$11 -> 0.05436 | D39: =Assumptions!$B$13*12*Assumptions!$B$11 -> 0.05436 | E39: =Assumptions!$B$13*12*Assumptions!$B$11 -> 0.05436 | F39: =Assumptions!$B$13*12*Assumptions!$B$11 -> 0.05436
A40: AI Cost as % of Revenue | B40: =IF(B17>0,B23/B17,0) -> 0.038448662 | C40: =IF(C17>0,C23/C17,0) -> 0.042934339 | D40: =IF(D17>0,D23/D17,0) -> 0.044504326 | E40: =IF(E17>0,E23/E17,0) -> 0.047255542 | F40: =IF(F17>0,F23/F17,0) -> 0.051422522
A41: Cost per Free User (taster) | B41: =Assumptions!$B$14 -> 0.00453 | C41: =Assumptions!$B$14 -> 0.00453 | D41: =Assumptions!$B$14 -> 0.00453 | E41: =Assumptions!$B$14 -> 0.00453 | F41: =Assumptions!$B$14 -> 0.00453

Sheet Conversion Scenarios
A1: CONVERSION RATE SENSITIVITY — YEAR 3 SNAPSHOT
A2: Shows Year 3 results at different conversion rates (200K downloads/yr)
A4: Metric | B4: 2% (Low) | C4: 3% (Conservative) | D4: 4% (Target) | E4: 5% (Optimistic) | F4: 7% (Stretch)
A5: New Pro Conversions | B5: 4000 | C5: 6000 | D5: 8000 | E5: 10000 | F5: 14000
A6: Gross Revenue | B6: 19960 | C6: 29940 | D6: 39920 | E6: 49900 | F6: 69860
A7: Net Revenue (after 15%) | B7: 16966 | C7: 25449 | D7: 33932 | E7: 42415 | F7: 59381
A8: AI Cost (taster + pro scans) | B8: 1366.248 | C8: 1596.372 | D8: 1826.496 | E8: 2056.62 | F8: 2516.868
A9: Net Profit (Year 3 only) | B9: 13383.952 | C9: 21628.428 | D9: 29872.904 | E9: 38117.38 | F9: 54606.332
A10: Cumulative 3-Year Profit (est.) | B10: 29444.694 | C10: 47582.542 | D10: 65720.389 | E10: 83858.236 | F10: 120133.93
A12: Taster Cost (all free users) | B12: 887.88 | C12: 878.82 | D12: 869.76 | E12: 860.7 | F12: 842.58
A13: Pro AI Cost (annual) | B13: 478.368 | C13: 717.552 | D13: 956.736 | E13: 1195.92 | F13: 1674.288
A14: Total AI Cost | B14: 1366.248 | C14: 1596.372 | D14: 1826.496 | E14: 2056.62 | F14: 2516.868
A15: AI as % of Net Revenue | B15: 0.080528587 | C15: 0.06272828 | D15: 0.053828127 | E15: 0.048488035 | F15: 0.042385073

Sheet Taster Cost Analysis
A1: FREE TASTER SCAN — COST ANALYSIS
A2: What does giving away 1 free AI scan to every user actually cost?
A4: THE MATH
A5: Downloads/Year | B5: Taster Scans | C5: Taster Cost | D5: Cost per Day
A6: 10000 | B6: 28800 | C6: 43.488 | D6: 0.11914521
A7: 50000 | B7: 144000 | C7: 217.44 | D7: 0.59572603
A8: 100000 | B8: 288000 | C8: 434.88 | D8: 1.1914521
A9: 200000 | B9: 576000 | C9: 869.76 | D9: 2.3829041
A10: 500000 | B10: 1440000 | C10: 2174.4 | D10: 5.9572603
A11: 1000000 | B11: 2880000 | C11: 4348.8 | D11: 11.914521
A13: KEY INSIGHT
A14: Even at 1 MILLION downloads/year, 3 taster scans cost just $4,348/year ($11.91/day).
A15: Compare to revenue: 1M downloads × 4% conversion × $4.99 × 85% = $169,660 net revenue.
A16: Taster cost is ~2.6% of revenue — still essentially a rounding error.
A18: VS. ALTERNATIVE: NO FREE SCAN
A19: Scenario | B19: Conversion Rate | C19: Pro Users | D19: Net Revenue
A20: With 3 taster scans (builds habit) | B20: 0.04 | C20: 8000 | D20: 33932
A21: Without taster (manual only free) | B21: 0.025 | C21: 5000 | D21: 21207.5
A22: Difference | B22: +1.5% | C22: +3,000 | D22: +$12,724
A24: 3 taster scans cost ~$869/yr at 200K downloads but likely generate $12,700+ in extra revenue.
A25: ROI on free tasters: ~1,400%. Still an absolute no-brainer.

Sheet Freemium vs Paid
A1: FREEMIUM vs PAID UPFRONT — HEAD TO HEAD
A3: Metric | B3: Paid $4.99 Upfront | C3: Freemium + $4.99 Unlock | D3: Winner
A4: Install Barrier | B4: HIGH — 65% bounce at paywall | C4: NONE — free download | D4: Freemium
A5: Year 1 Downloads (realistic) | B5: 5,000 - 15,000 | C5: 50,000+ | D5: Freemium
A6: Conversion/Purchase Rate | B6: 100% (all paid) | C6: 4% convert to Pro | D6: Paid (per-user)
A7: Year 1 Paying Users | B7: 5,000 - 15,000 | C7: 2,000 (50K × 4%) | D7: Paid
A8: Year 1 Net Revenue | B8: $21K - $64K | C8: $8.5K | D8: Paid (if downloads hold)
A9: Year 3 Downloads | B9: 10,000 - 20,000 | C9: 200,000 | D9: Freemium (10-20×)
A10: Year 3 Paying Users | B10: 10,000 - 20,000 | C10: 8,000 | D10: Depends
A11: Year 3 Net Revenue | B11: $42K - $85K | C11: $34K | D11: Close
A12: App Store Ranking | B12: LOW — few downloads | C12: HIGH — many downloads | D12: Freemium
A13: Organic Discovery | B13: Very difficult | C13: Downloads boost ranking | D13: Freemium
A14: Word of Mouth | B14: Limited reach | C14: Large free user base | D14: Freemium
... A18: Long-term Upside | B18: Linear (pay-per-download) | C18: Exponential (network effects) | D18: Freemium
A20: VERDICT
A21: Freemium wins 10/15 categories. Paid upfront generates more revenue per user but
A22: dramatically limits discovery and growth. In a crowded App Store, visibility IS revenue.

Sheet Strategy
A1: RECOMMENDED PRICING STRATEGY
A3: FREE TIER
A4: Subscriptions | B4: 3 max
A5: Entry Method | B5: Manual only
A6: AI Screenshot Scan | B6: 3 free scans (lifetime)
A7: Reminders | B7: Basic (day-of only)
A8: Money Saved Tracker | B8: No
A9: Widgets | B9: No
A10: Siri Shortcuts | B10: No
A11: Price | B11: FREE
A13: PRO UNLOCK
A14: Subscriptions | B14: Unlimited
A15: Entry Method | B15: Manual + AI Screenshot Scan
A16: AI Screenshot Scan | B16: Unlimited
A17: Reminders | B17: Smart escalating (7d, 3d, 1d, morning-of)
A18: Money Saved Tracker | B18: Yes (gamification)
A19: Widgets | B19: Yes (home screen widget)
A20: Siri Shortcuts | B20: Yes
A21: Trial Countdown | B21: Yes (urgent trial tracking)
A22: Price | B22: $4.99 one-time lifetime unlock
A24: CONVERSION TRIGGERS
A25: 1. Taster wow moment | B25: User screenshots subscription → AI fills everything → 'Unlock unlimited scans'
A26: 2. Subscription limit hit | B26: User adds 6th subscription → soft paywall
A27: 3. Trial urgency | B27: 'Your Netflix trial ends in 3 days' → 'Get smart reminders with Pro'
A28: 4. Money saved tease | B28: 'You could be tracking $X/month in savings' → 'Unlock with Pro'
A29: 5. Post-renewal regret | B29: 'You just got charged $14.99. Never miss a renewal → Go Pro'
